ds_helpers/__init__.py
ds_helpers/helpers.py
ds_helpers-0.1.1.dist-info/LICENSE
ds_helpers-0.1.1.dist-info/METADATA
ds_helpers-0.1.1.dist-info/WHEEL
ds_helpers-0.1.1.dist-info/top_level.txt
ds_helpers-0.1.1.dist-info/RECORD
