Metadata-Version: 2.1
Name: ds-helpers
Version: 0.1.1
Summary: Helper functions for Data analysis and modeling
Home-page: https://github.com/shashankwadhwa9/ds-helpers
Author: Shashank Wadhwa
Author-email: shashankwadhwa9@gmail.com
License: UNKNOWN
Platform: UNKNOWN
Classifier: Programming Language :: Python :: 3
Classifier: License :: OSI Approved :: MIT License
Classifier: Operating System :: OS Independent
Requires-Dist: numpy
Requires-Dist: pandas
Requires-Dist: matplotlib
Requires-Dist: seaborn
Requires-Dist: sklearn
